light_agents/__init__.py
light_agents/ai_agents/__init__.py
light_agents/ai_agents/claude_agent.py
light_agents/ai_agents/openai_agent.py
light_agents/config.py
light_agents/core/logger_config.py
light_agents/core/tool_registry.py
light_agents/exceptions/__init__.py
light_agents/exceptions/messages_exceptions.py
light_agents/exceptions/thread_agent_exceptions.py
light_agents/schemas/__init__.py
light_agents/schemas/messages_schemas.py
light_agents/schemas/model_config.py
light_agents/schemas/thread_agent_schema.py
light_agents/schemas/thread_schema.py
light_agents/schemas/tool_schema.py
light_agents/serializers/__init__.py
light_agents/serializers/messages/__init__.py
light_agents/serializers/messages/claude_messages_serializers.py
light_agents/serializers/messages/openai_messages_serializer.py
light_agents/serializers/tools/__init__.py
light_agents/serializers/tools/base_serializers.py
light_agents/serializers/tools/claude_tools_serializer.py
light_agents/serializers/tools/openai_tools_serializer.py
light_agents/utils/__init__.py
light_agents/utils/serializers.py
light_agents-0.1.2.dist-info/METADATA
light_agents-0.1.2.dist-info/WHEEL
light_agents-0.1.2.dist-info/RECORD
